LICENSE.md
MANIFEST.in
README.md
pyproject.toml
src/raspa_ase/__init__.py
src/raspa_ase/calculator.py
src/raspa_ase/py.typed
src/raspa_ase.egg-info/PKG-INFO
src/raspa_ase.egg-info/SOURCES.txt
src/raspa_ase.egg-info/dependency_links.txt
src/raspa_ase.egg-info/requires.txt
src/raspa_ase.egg-info/top_level.txt
src/raspa_ase/utils/__init__.py
src/raspa_ase/utils/dicts.py
src/raspa_ase/utils/io.py
src/raspa_ase/utils/params.py
tests/test_calculator.py